doiget_tdm/__init__.py
doiget_tdm/acquire.py
doiget_tdm/cli.py
doiget_tdm/config.py
doiget_tdm/crossref.py
doiget_tdm/data.py
doiget_tdm/doi.py
doiget_tdm/errors.py
doiget_tdm/format.py
doiget_tdm/fulltext.py
doiget_tdm/generic.py
doiget_tdm/log.py
doiget_tdm/metadata.py
doiget_tdm/paths.py
doiget_tdm/publisher.py
doiget_tdm/py.typed
doiget_tdm/source.py
doiget_tdm/status.py
doiget_tdm/validate.py
doiget_tdm/web.py
doiget_tdm/work.py
doiget_tdm/publishers/__init__.py
doiget_tdm/publishers/_ama.py
doiget_tdm/publishers/_apa.py
doiget_tdm/publishers/_elsevier.py
doiget_tdm/publishers/_frontiers.py
doiget_tdm/publishers/_iop.py
doiget_tdm/publishers/_peerj.py
doiget_tdm/publishers/_plos.py
doiget_tdm/publishers/_pnas.py
doiget_tdm/publishers/_royal_society.py
doiget_tdm/publishers/_sage.py
doiget_tdm/publishers/_springer_nature.py
doiget_tdm/publishers/_taylor_and_francis.py
doiget_tdm/publishers/_wiley.py
doiget_tdm-0.1.0.dist-info/METADATA
doiget_tdm-0.1.0.dist-info/WHEEL
doiget_tdm-0.1.0.dist-info/entry_points.txt
doiget_tdm-0.1.0.dist-info/licenses/LICENSE
doiget_tdm-0.1.0.dist-info/RECORD
