Metadata-Version: 2.4
Name: doiget-tdm
Version: 0.1.0
Summary: A command-line application and Python library for obtaining the metadata and full-text of published journal articles for text data mining (TDM) purposes.
Project-URL: Documentation, https://unimelbmdap.github.io/doiget-tdm
Project-URL: Repository, https://github.com/unimelbmdap/doiget-tdm
Project-URL: Issues, https://github.com/unimelbmdap/doiget-tdm/issues
Author-email: Damien Mannion <damien.mannion@unimelb.edu.au>
License-Expression: MIT
License-File: LICENSE
Classifier: License :: OSI Approved :: MIT License
Classifier: Operating System :: OS Independent
Classifier: Programming Language :: Python :: 3
Classifier: Programming Language :: Python :: 3.11
Classifier: Programming Language :: Python :: 3.12
Requires-Python: <3.13,>=3.11
Requires-Dist: alive-progress>=3.1.5
Requires-Dist: crossref-lmdb>=0.1.2
Requires-Dist: html5lib>=1.1
Requires-Dist: limiter>=0.5.0
Requires-Dist: more-itertools>=10.5.0
Requires-Dist: platformdirs>=4.3.6
Requires-Dist: polars-lts-cpu[xlsxwriter]>=1.14.0
Requires-Dist: puremagic>=1.27
Requires-Dist: py7zr>=0.22.0
Requires-Dist: pydantic-settings>=2.5.2
Requires-Dist: pydantic[email]>=2.9.2
Requires-Dist: pyrage>=1.2.1
Requires-Dist: pyrate-limiter>=2.10.0
Requires-Dist: pysftp>=0.2.9
Requires-Dist: pysimdjson>=6.0.2
Requires-Dist: requests-ratelimiter>=0.7.0
Requires-Dist: requests>=2.32.3
Requires-Dist: retryhttp[requests]>=1.1.0
Requires-Dist: rich>=13.9.4
Requires-Dist: tenacity>=9.0.0
Requires-Dist: tzdata>=2024.1
Requires-Dist: universal-pathlib>=0.2.5
Provides-Extra: docs
Requires-Dist: autodoc-pydantic>=2.2.0; extra == 'docs'
Requires-Dist: enum-tools[sphinx]>=0.12.0; extra == 'docs'
Requires-Dist: furo>=2024.8.6; extra == 'docs'
Requires-Dist: sphinx-argparse-cli>=1.18.2; extra == 'docs'
Requires-Dist: sphinx-argparse>=0.5.2; extra == 'docs'
Requires-Dist: sphinx-autobuild>=2024.10.3; extra == 'docs'
Requires-Dist: sphinx-autodoc-typehints>=2.4.4; extra == 'docs'
Requires-Dist: sphinx-toolbox>=3.8.0; extra == 'docs'
Requires-Dist: sphinx>=8.0.2; extra == 'docs'
Provides-Extra: interactive
Requires-Dist: ipython>=8.27.0; extra == 'interactive'
Provides-Extra: lmdb
Requires-Dist: lmdb>=1.5.1; extra == 'lmdb'
